scraper/__init__.py
scraper/admin.py
scraper/apps.py
scraper/migrations/0001_initial.py
scraper/migrations/__init__.py
scraper/models.py
scraper/scraper.py
scraper/tests.py
scraper/views.py
django_webscraper-0.0.2.dist-info/LICENSE
django_webscraper-0.0.2.dist-info/METADATA
django_webscraper-0.0.2.dist-info/WHEEL
django_webscraper-0.0.2.dist-info/RECORD
