Metadata-Version: 2.1
Name: django-webscraper
Version: 0.0.2
Summary: A standalone Django app for scraping websites
Author: Martin Kjellberg
Author-email: martin@kjellberg.io
Requires-Python: >=3.11,<4.0
Classifier: Programming Language :: Python :: 3
Classifier: Programming Language :: Python :: 3.11
